aws_sam_translator-1.107.0.dist-info/licenses/LICENSE
aws_sam_translator-1.107.0.dist-info/licenses/NOTICE
aws_sam_translator-1.107.0.dist-info/licenses/THIRD_PARTY_LICENSES
samtranslator/__init__.py
samtranslator/compat.py
samtranslator/region_configuration.py
samtranslator/yaml_helper.py
samtranslator/feature_toggle/__init__.py
samtranslator/feature_toggle/dialup.py
samtranslator/feature_toggle/feature_toggle.py
samtranslator/internal/__init__.py
samtranslator/internal/deprecation_control.py
samtranslator/internal/intrinsics.py
samtranslator/internal/managed_policies.py
samtranslator/internal/types.py
samtranslator/internal/data/aws_managed_policies.json
samtranslator/internal/model/__init__.py
samtranslator/internal/model/appsync.py
samtranslator/internal/schema_source/__init__.py
samtranslator/internal/schema_source/any_cfn_resource.py
samtranslator/internal/schema_source/aws_serverless_api.py
samtranslator/internal/schema_source/aws_serverless_application.py
samtranslator/internal/schema_source/aws_serverless_capacity_provider.py
samtranslator/internal/schema_source/aws_serverless_connector.py
samtranslator/internal/schema_source/aws_serverless_function.py
samtranslator/internal/schema_source/aws_serverless_graphqlapi.py
samtranslator/internal/schema_source/aws_serverless_httpapi.py
samtranslator/internal/schema_source/aws_serverless_layerversion.py
samtranslator/internal/schema_source/aws_serverless_simpletable.py
samtranslator/internal/schema_source/aws_serverless_statemachine.py
samtranslator/internal/schema_source/common.py
samtranslator/internal/schema_source/sam-docs.json
samtranslator/internal/schema_source/schema.py
samtranslator/internal/utils/__init__.py
samtranslator/internal/utils/utils.py
samtranslator/intrinsics/__init__.py
samtranslator/intrinsics/actions.py
samtranslator/intrinsics/resolver.py
samtranslator/intrinsics/resource_refs.py
samtranslator/metrics/__init__.py
samtranslator/metrics/method_decorator.py
samtranslator/metrics/metrics.py
samtranslator/model/__init__.py
samtranslator/model/apigateway.py
samtranslator/model/apigatewayv2.py
samtranslator/model/architecture.py
samtranslator/model/cloudformation.py
aws_sam_translator-1.107.0.dist-info/METADATA
aws_sam_translator-1.107.0.dist-info/WHEEL
aws_sam_translator-1.107.0.dist-info/top_level.txt
aws_sam_translator-1.107.0.dist-info/RECORD
