Metadata-Version: 2.4
Name: aws-sam-translator
Version: 1.107.0
Summary: AWS SAM Translator is a library that transform SAM templates into AWS CloudFormation templates
Home-page: https://github.com/awslabs/serverless-application-model
Author: Amazon Web Services
Author-email: aws-sam-developers@amazon.com
License: Apache License 2.0
Keywords: AWS SAM Serverless Application Model
Classifier: Development Status :: 5 - Production/Stable
Classifier: Environment :: Console
Classifier: Environment :: Other Environment
Classifier: Intended Audience :: Developers
Classifier: Intended Audience :: Information Technology
Classifier: License :: OSI Approved :: Apache Software License
Classifier: Operating System :: OS Independent
Classifier: Programming Language :: Python
Classifier: Programming Language :: Python :: 3.8
Classifier: Programming Language :: Python :: 3.9
Classifier: Programming Language :: Python :: 3.10
Classifier: Programming Language :: Python :: 3.11
Classifier: Topic :: Internet
Classifier: Topic :: Software Development :: Build Tools
Classifier: Topic :: Utilities
Requires-Python: >=3.8, <=4.0, !=4.0
License-File: LICENSE
License-File: NOTICE
License-File: THIRD_PARTY_LICENSES
Requires-Dist: boto3<2.0.0,>=1.34.0
Requires-Dist: jsonschema<5,>=4.23
Requires-Dist: typing_extensions>=4.4
Requires-Dist: pydantic>=2.10.6; python_version >= "3.8"
Requires-Dist: pydantic~=2.12.5; python_version >= "3.9"
Provides-Extra: dev
Requires-Dist: coverage<8,>=5.3; extra == "dev"
Requires-Dist: pytest-cov<5,>=2.10; extra == "dev"
Requires-Dist: pytest-xdist<4,>=2.5; extra == "dev"
Requires-Dist: pytest-env<1,>=0.6; extra == "dev"
Requires-Dist: pytest-rerunfailures<12,>=9.1; extra == "dev"
Requires-Dist: pyyaml~=6.0; extra == "dev"
Requires-Dist: ruff~=0.4.5; extra == "dev"
Requires-Dist: pytest<8,>=6.2; extra == "dev"
Requires-Dist: parameterized~=0.7; extra == "dev"
Requires-Dist: dateparser~=1.1; extra == "dev"
Requires-Dist: boto3<2.0.0,>=1.34.0; extra == "dev"
Requires-Dist: tenacity~=9.0; extra == "dev"
Requires-Dist: requests~=2.28; extra == "dev"
Requires-Dist: black==24.3.0; extra == "dev"
Requires-Dist: ruamel.yaml==0.17.21; extra == "dev"
Requires-Dist: mypy~=1.10.1; extra == "dev"
Requires-Dist: boto3-stubs[appconfig,serverlessrepo]<2.0.0,>=1.34.0; extra == "dev"
Requires-Dist: types-PyYAML~=6.0; extra == "dev"
Requires-Dist: types-jsonschema~=3.2; extra == "dev"
Dynamic: author
Dynamic: author-email
Dynamic: classifier
Dynamic: description
Dynamic: description-content-type
Dynamic: home-page
Dynamic: keywords
Dynamic: license
Dynamic: license-file
Dynamic: provides-extra
Dynamic: requires-dist
Dynamic: requires-python
Dynamic: summary
